moduconfig/__init__.py
moduconfig-0.0.1.dist-info/LICENSE.md
moduconfig-0.0.1.dist-info/METADATA
moduconfig-0.0.1.dist-info/WHEEL
moduconfig-0.0.1.dist-info/top_level.txt
moduconfig-0.0.1.dist-info/RECORD
