Metadata-Version: 2.1
Name: moduconfig
Version: 0.0.1
Summary: A declarative and powerful configuration APIfor application configuration and documentation
Home-page: https://github.com/Moro-Code/moduconfig
Author: Omar Nasr
Author-email: omar@omarnasr.ca
License: UNKNOWN
Platform: UNKNOWN
Classifier: Programming Language :: Python :: 3 :: Only
Classifier: License :: OSI Approved :: MIT License
Classifier: Operating System :: OS Independent
Classifier: Development Status :: 1 - Planning
Classifier: Intended Audience :: Information Technology
Classifier: Intended Audience :: System Administrators
Classifier: Topic :: Software Development :: Documentation
Classifier: Topic :: Software Development :: Libraries
Requires-Python: >=3.5
